pyvtorch/__init__.py
pyvtorch/aux.py
pyvtorch/dataset.py
pyvtorch/image.py
pyvtorch/trainer.py
pyvtorch-1.3.1.dist-info/licenses/LICENSE
pyvtorch-1.3.1.dist-info/METADATA
pyvtorch-1.3.1.dist-info/WHEEL
pyvtorch-1.3.1.dist-info/top_level.txt
pyvtorch-1.3.1.dist-info/RECORD
