Metadata-Version: 2.4
Name: pyvtorch
Version: 1.3.1
Summary: Python tools to work in deep learning with PyTorch
Author-email: Valeria Pais <valeriarpais@gmail.com>
License: MIT License
Project-URL: Repository, https://github.com/0xInfty/PyVTorch.git
Project-URL: Homepage, https://github.com/0xInfty/PyVTorch
Project-URL: Issues, https://github.com/0xInfty/PyVTorch/issues
Keywords: deep learning,pytorch
Classifier: Development Status :: 3 - Alpha
Classifier: License :: OSI Approved :: MIT License
Classifier: Programming Language :: Python :: 3
Requires-Python: >=3.12.0
License-File: LICENSE
Requires-Dist: pyvtools
Requires-Dist: torch
Requires-Dist: torchvision
Requires-Dist: numpy
Requires-Dist: matplotlib
Requires-Dist: h5py
Requires-Dist: tqdm
Requires-Dist: scikit-image
Requires-Dist: scikit-learn
Dynamic: license-file
